google/cloud/spark_connect/__init__.py
google/cloud/spark_connect/exceptions.py
google/cloud/spark_connect/session.py
google/cloud/spark_connect/client/__init__.py
google/cloud/spark_connect/client/core.py
google/cloud/spark_connect/client/proxy.py
google_spark_connect-0.5.6.dist-info/LICENSE
google_spark_connect-0.5.6.dist-info/METADATA
google_spark_connect-0.5.6.dist-info/WHEEL
google_spark_connect-0.5.6.dist-info/top_level.txt
google_spark_connect-0.5.6.dist-info/RECORD
