Metadata-Version: 2.1
Name: google-spark-connect
Version: 0.5.6
Summary: Google client library for Spark Connect
Home-page: https://github.com/GoogleCloudDataproc/dataproc-spark-connect-python
Author: Google LLC
License: Apache 2.0
License-File: LICENSE
Requires-Dist: google-api-core>=2.19.1
Requires-Dist: google-cloud-dataproc>=5.18.0
Requires-Dist: websockets
Requires-Dist: pyspark[connect]>=3.5
